benchmarks/IRT.py
benchmarks/__init__.py
benchmarks/benchmarks_mchmc.py
benchmarks/benchmarks_numpyro.py
benchmarks/brownian.py
benchmarks/german_credit.py
mclmc/__init__.py
mclmc/annealing.py
mclmc/correlation_length.py
mclmc/dynamics.py
mclmc/old_annealing.py
mclmc/sampler.py
mclmc/smc.py
tests/__init__.py
tests/benchmarks.py
tests/test_annealing.py
tests/test_mclmc.py
tests/test_momentum_update.py
tests/tst_diagonal_precond.py
mclmc-0.2.6.dist-info/LICENSE.md
mclmc-0.2.6.dist-info/METADATA
mclmc-0.2.6.dist-info/WHEEL
mclmc-0.2.6.dist-info/top_level.txt
mclmc-0.2.6.dist-info/RECORD
