Metadata-Version: 2.1
Name: mclmc
Version: 0.2.6
Summary: Faster gradient based sampling
Author-email: Jakob Robnik <jakob.robnik@gmail.com>
License: LICENSE.md
License-File: LICENSE.md
Requires-Dist: jax >=0.4
Requires-Dist: jaxlib >=0.4
Requires-Dist: numpy >=1.26
Requires-Dist: mypy >=1.7
Requires-Dist: pre-commit >=3.5
Requires-Dist: matplotlib >=3.8
Requires-Dist: pandas >=2.1
Requires-Dist: pytest >=7.2
Requires-Dist: pytest-benchmark >=3.2
